pofmt-0.4.0.dist-info/METADATA
pofmt-0.4.0.dist-info/WHEEL
pofmt-0.4.0.dist-info/entry_points.txt
pofmt-0.4.0.dist-info/licenses/LICENSE
pofmt/__init__.py
pofmt/__main__.py
pofmt/core.py
pofmt-0.4.0.dist-info/RECORD
