Metadata-Version: 2.1
Name: pofmt
Version: 0.4.0
Summary: Your missing PO formatter and linter
Author-Email: Frost Ming <mianghong@gmail.com>
License: MIT
Classifier: Development Status :: 3 - Alpha
Classifier: Programming Language :: Python
Classifier: Programming Language :: Python :: 3
Project-URL: Repository, https://github.com/frostming/pofmt
Project-URL: Homepage, https://github.com/frostming/pofmt
Requires-Python: >=3.7
Provides-Extra: zh
Requires-Dist: pangu>=4.0; extra == "zh"
